vedicastro/VedicAstro.py
vedicastro/__init__.py
vedicastro/horary_chart.py
vedicastro/utils.py
vedicastro/data/KP_SL_Divisions.csv
vedicastro-0.2.1.dist-info/METADATA
vedicastro-0.2.1.dist-info/WHEEL
vedicastro-0.2.1.dist-info/dependency_links.txt
vedicastro-0.2.1.dist-info/top_level.txt
vedicastro-0.2.1.dist-info/RECORD
