Metadata-Version: 2.1
Name: vedicastro
Version: 0.2.1
Summary: A python package for Vedic Astrology, with a particular focus on the Krishnamurthi Paddhati system
Home-page: https://github.com/diliprk/VedicAstro
Author: Dilip Rajkumar
Author-email: diliprajkumar@gmail.com
License: MIT
Classifier: Programming Language :: Python :: 3
Classifier: License :: OSI Approved :: MIT License
Classifier: Operating System :: OS Independent
Requires-Python: >=3.11
Requires-Dist: tqdm
Requires-Dist: polars
Requires-Dist: fastapi
Requires-Dist: uvicorn
Requires-Dist: prettytable
Requires-Dist: ipykernel
Requires-Dist: pyswisseph
